ChangeLog.txt
LICENSE.txt
MANIFEST.in
README.txt
TODO.txt
setup.py
esky/__init__.py
esky/bootstrap.py
esky/errors.py
esky/finder.py
esky/fstransact.py
esky/util.py
esky/winres.py
esky.egg-info/PKG-INFO
esky.egg-info/SOURCES.txt
esky.egg-info/dependency_links.txt
esky.egg-info/top_level.txt
esky/bdist_esky/__init__.py
esky/bdist_esky/f_bbfreeze.py
esky/bdist_esky/f_py2exe.py
esky/tests/__init__.py
esky/tests/test_esky.py
esky/tests/build/bdist.win32/winexe/temp/_ctypes.py
esky/tests/build/bdist.win32/winexe/temp/_hashlib.py
esky/tests/build/bdist.win32/winexe/temp/_socket.py
esky/tests/build/bdist.win32/winexe/temp/_ssl.py
esky/tests/build/bdist.win32/winexe/temp/bz2.py
esky/tests/build/bdist.win32/winexe/temp/select.py
esky/tests/build/bdist.win32/winexe/temp/unicodedata.py
esky/tests/build/bdist.win32/winexe/temp/win32gui.py
esky/tests/build/lib/eskytester/__init__.py
esky/tests/build/lib/eskytester/pkgdata.txt
esky/tests/build/lib/eskytester/script1.py
esky/tests/build/lib/eskytester/script2.py
esky/tests/build/lib/eskytester/script3.py
esky/tests/build/scripts-2.6/script1.py
esky/tests/build/scripts-2.6/script2.py
esky/tests/build/scripts-2.6/script3.py
esky/tests/deploy.linux-i686/eskytester-0.3.linux-i686/esky-bootstrap.txt
esky/tests/deploy.linux-i686/eskytester-0.3.linux-i686/data/datafile.txt
esky/tests/deploy.win32/eskytester-0.3.win32/esky-bootstrap.txt
esky/tests/deploy.win32/eskytester-0.3.win32/data/datafile.txt
esky/tests/eskytester/__init__.py
esky/tests/eskytester/datafile.txt
esky/tests/eskytester/pkgdata.txt
esky/tests/eskytester/script1.py
esky/tests/eskytester/script2.py
esky/tests/eskytester/script3.py