Metadata-Version: 1.0
Name: esky
Version: 0.3.0
Summary: keep frozen apps fresh
Home-page: http://github.com/clouddotme/esky/
Author: Ryan Kelly
Author-email: rfk@cloud.me
License: BSD
Keywords: update auto-update freeze
Platform: UNKNOWN
